dspyce/__init__.py
dspyce/models.py
dspyce/_testing/__init__.py
dspyce/_testing/bitstreamTest.py
dspyce/_testing/dspyceTest.py
dspyce/_testing/itemTests.py
dspyce/_testing/metadataTests.py
dspyce/_testing/relationTest.py
dspyce/_testing/restTest.py
dspyce/_testing/safTest.py
dspyce/_testing/statisticsTest.py
dspyce/bitstreams/__init__.py
dspyce/bitstreams/models.py
dspyce/entities/__init__.py
dspyce/entities/models.py
dspyce/metadata/__init__.py
dspyce/metadata/models.py
dspyce/rest/__init__.py
dspyce/rest/exceptions.py
dspyce/rest/functions.py
dspyce/rest/models.py
dspyce/saf/__init__.py
dspyce/saf/saf_read.py
dspyce/saf/saf_write.py
dspyce/statistics/__init__.py
dspyce/statistics/retrieve.py
dspyce-0.1.dist-info/LICENSE
dspyce-0.1.dist-info/METADATA
dspyce-0.1.dist-info/WHEEL
dspyce-0.1.dist-info/top_level.txt
dspyce-0.1.dist-info/RECORD
