Metadata-Version: 2.2
Name: dspyce
Version: 0.1
Summary: The *dspyce* package helps to communicate with dspace interfaces. Currently saf (Simple Archive Format) packages and the RestAPI are supported.
Author: Löhden, Eike Martin
Project-URL: Homepage, https://github.com/dspace-unimr/dspyce
Project-URL: Issues, https://github.com/dspace-unimr/dspyce/issues
Project-URL: Institution, https://www.uni-marburg.de/en/ub
Classifier: Programming Language :: Python :: 3.10
Classifier: License :: OSI Approved :: MIT License
Classifier: Operating System :: OS Independent
Requires-Python: >=3.10
License-File: LICENSE
Requires-Dist: pillow>=10.0.0
Requires-Dist: requests>=2.28.0
Requires-Dist: beautifulsoup4>=4.0
Requires-Dist: lxml>=5.0
Requires-Dist: networkx>=3.3
Requires-Dist: matplotlib>=3.6
